lxm3-0.4.3.dist-info/METADATA
lxm3-0.4.3.dist-info/WHEEL
lxm3-0.4.3.dist-info/entry_points.txt
lxm3/__init__.py
lxm3/_vendor/xmanager/LICENSE
lxm3/_vendor/xmanager/bazel/client.py
lxm3/_vendor/xmanager/bazel/file_utils.py
lxm3/_vendor/xmanager/xm/README.md
lxm3/_vendor/xmanager/xm/__init__.py
lxm3/_vendor/xmanager/xm/async_packager.py
lxm3/_vendor/xmanager/xm/compute_units.py
lxm3/_vendor/xmanager/xm/core.py
lxm3/_vendor/xmanager/xm/executables.py
lxm3/_vendor/xmanager/xm/id_predictor.py
lxm3/_vendor/xmanager/xm/job_blocks.py
lxm3/_vendor/xmanager/xm/job_operators.py
lxm3/_vendor/xmanager/xm/metadata_context.py
lxm3/_vendor/xmanager/xm/packagables.py
lxm3/_vendor/xmanager/xm/packagables_generator.py
lxm3/_vendor/xmanager/xm/pattern_matching.py
lxm3/_vendor/xmanager/xm/resources.py
lxm3/_vendor/xmanager/xm/utils.py
lxm3/_vendor/xmanager/xm_mock/__init__.py
lxm3/cli/clean.py
lxm3/cli/cli.py
lxm3/cli/shell.py
lxm3/clusters/gridengine.py
lxm3/clusters/slurm.py
lxm3/contrib/ucl.py
lxm3/contrib/wandb.py
lxm3/experimental/__init__.py
lxm3/experimental/image_cache.py
lxm3/experimental/job_script_builder.py
lxm3/singularity/__init__.py
lxm3/singularity/images.py
lxm3/singularity/uri.py
lxm3/xm/__init__.py
lxm3/xm_cluster/__init__.py
lxm3/xm_cluster/array_job.py
lxm3/xm_cluster/artifacts.py
lxm3/xm_cluster/config.py
lxm3/xm_cluster/console.py
lxm3/xm_cluster/executable_specs.py
lxm3/xm_cluster/executables.py
lxm3/xm_cluster/execution/__init__.py
lxm3/xm_cluster/execution/gridengine.py
lxm3/xm_cluster/execution/job_script_builder.py
lxm3/xm_cluster/execution/local.py
lxm3/xm_cluster/execution/slurm.py
lxm3/xm_cluster/execution/utils.py
lxm3/xm_cluster/executors.py
lxm3/xm_cluster/experiment.py
lxm3/xm_cluster/metadata.py
lxm3/xm_cluster/packaging/__init__.py
lxm3/xm_cluster/packaging/archive_builder.py
lxm3/xm_cluster/packaging/cluster.py
lxm3/xm_cluster/packaging/container_builder.py
lxm3/xm_cluster/packaging/digest_util.py
lxm3/xm_cluster/packaging/local.py
lxm3/xm_cluster/packaging/router.py
lxm3/xm_cluster/requirements.py
lxm3-0.4.3.dist-info/RECORD
