Metadata-Version: 2.1
Name: lxm3
Version: 0.4.3
Summary: LXM3: XManager launch backend for HPC clusters
Keywords: machine-learning hpc packaging singularity
Home-page: https://github.com/ethanluoyc/lxm3
Author-Email: Yicheng Luo <ethanluoyc@gmail.com>
License: MIT
Classifier: Development Status :: 4 - Beta
Classifier: Programming Language :: Python
Classifier: Programming Language :: Python :: 3
Classifier: Programming Language :: Python :: 3.9
Classifier: Programming Language :: Python :: 3.10
Classifier: Programming Language :: Python :: 3.11
Classifier: Programming Language :: Python :: Implementation :: CPython
Project-URL: Homepage, https://github.com/ethanluoyc/lxm3
Project-URL: Documentation, https://lxm3.readthedocs.io/en/latest/
Project-URL: Repository, https://github.com/ethanluoyc/lxm3
Requires-Python: <3.13,>=3.9
Requires-Dist: absl-py
Requires-Dist: attrs
Requires-Dist: ml_collections
Requires-Dist: tomlkit
Requires-Dist: paramiko
Requires-Dist: fabric
Requires-Dist: appdirs
Requires-Dist: fsspec
Requires-Dist: async_generator
Requires-Dist: immutabledict
Requires-Dist: rich
Requires-Dist: vcsinfo
Requires-Dist: docker
Requires-Dist: pip
Requires-Dist: shelved-cache>=0.3.1
Requires-Dist: cachetools>=5.3.2
Requires-Dist: IPython; extra == "shell"
Requires-Dist: pex>2.1.139; extra == "pex"
Provides-Extra: shell
Provides-Extra: pex
